hotvox_client/__init__.py
hotvox_client/_client.py
hotvox_client/base.py
hotvox_client-1.37.1.dist-info/LICENSE
hotvox_client-1.37.1.dist-info/METADATA
hotvox_client-1.37.1.dist-info/WHEEL
hotvox_client-1.37.1.dist-info/entry_points.txt
hotvox_client-1.37.1.dist-info/top_level.txt
hotvox_client-1.37.1.dist-info/RECORD
