Metadata-Version: 2.1
Name: hotvox_client
Version: 1.37.1
Summary: Awesome hotvox_client created by hotvox
Home-page: https://github.com/hotvox/hotvox-client-python/
Author: hotvox
License-File: LICENSE
Requires-Dist: openai ==1.37.1
Provides-Extra: test
Requires-Dist: pytest ; extra == 'test'
Requires-Dist: coverage ; extra == 'test'
Requires-Dist: flake8 ; extra == 'test'
Requires-Dist: black ; extra == 'test'
Requires-Dist: isort ; extra == 'test'
Requires-Dist: pytest-cov ; extra == 'test'
Requires-Dist: mypy ; extra == 'test'
Requires-Dist: gitchangelog ; extra == 'test'
Requires-Dist: mkdocs ; extra == 'test'
